{
  "address": "BKRPzmuiy84FuBdbbjAa1Nk8LJ2CKekVhJXi1NqTxCh9",
  "metadata": {
    "name": "PerpNexus",
    "version": "0.1.0",
    "spec": "0.1.0",
    "description": "Created with Anchor"
  },
  "instructions": [
    {
      "name": "init_perp_config",
      "discriminator": [
        243,
        145,
        211,
        0,
        200,
        68,
        99,
        85
      ],
      "accounts": [
        {
          "name": "admin",
          "writable": true,
          "signer": true
        },
        {
          "name": "config",
          "writable": true,
          "pda": {
            "seeds": [
              {
                "kind": "const",
                "value": [
                  99,
                  111,
                  110,
                  102,
                  105,
                  103
                ]
              }
            ]
          }
        },
        {
          "name": "protocol_vault",
          "pda": {
            "seeds": [
              {
                "kind": "const",
                "value": [
                  118,
                  97,
                  117,
                  108,
                  116
                ]
              }
            ]
          }
        },
        {
          "name": "system_program",
          "address": "11111111111111111111111111111111"
        }
      ],
      "args": [
        {
          "name": "cranker",
          "type": "pubkey"
        },
        {
          "name": "fees",
          "type": "u16"
        }
      ]
    }
  ],
  "accounts": [
    {
      "name": "PerpNexusConfig",
      "discriminator": [
        31,
        122,
        184,
        34,
        246,
        243,
        2,
        211
      ]
    }
  ],
  "types": [
    {
      "name": "PerpNexusConfig",
      "type": {
        "kind": "struct",
        "fields": [
          {
            "name": "admin",
            "type": "pubkey"
          },
          {
            "name": "cranker",
            "type": "pubkey"
          },
          {
            "name": "fees",
            "type": "u16"
          },
          {
            "name": "bump",
            "type": "u8"
          }
        ]
      }
    }
  ]
}